kunapipy/__init__.py
kunapipy/asynkundelik/__init__.py
kunapipy/asynkundelik/exceptions.py
kunapipy/asynkundelik/kundelik.py
kunapipy/asynkundelik/utils.py
kunapipy/kundelik/__init__.py
kunapipy/kundelik/exceptions.py
kunapipy/kundelik/kundelik.py
kunapipy-0.1.0.dist-info/LICENSE
kunapipy-0.1.0.dist-info/WHEEL
kunapipy-0.1.0.dist-info/METADATA
kunapipy-0.1.0.dist-info/RECORD
