Metadata-Version: 2.1
Name: kunapipy
Version: 0.1.0
Summary: Simple wrapper for kundelik.kz API, based on pydnevnikruapi
Author: kesha1225
Author-email: samedov03@mail.ru
Requires-Python: >=3.7,<4.0
Classifier: Programming Language :: Python :: 3
Classifier: Programming Language :: Python :: 3.10
Classifier: Programming Language :: Python :: 3.7
Classifier: Programming Language :: Python :: 3.8
Classifier: Programming Language :: Python :: 3.9
Requires-Dist: aiohttp (>=3.7.4,<4.0.0)
Requires-Dist: requests (>=2.22.0,<3.0.0)
